[
  {
    "dn": "cn=usCiv,o=MyCa Org,c=US",
    "displayName": "US Civilian",
    "employeeId": "usCiv",
    "fullName": "US Civilian",
    "lastName": "Civilian",
    "uid": "usCiv",
    "clearances": ["TOP SECRET", "SECRET", "CONFIDENTIAL", "UNCLASSIFIED"],
    "formalAccess": ["foo", "bar"],
    "country": "USA",
    "affiliations": ["CIVILIAN"],
    "coi": [],
    "briefing": [],
    "formalGroup": [],
    "grantBy": [],
    "dissemControl": [],
    "organization": [],
    "dissemTo": []
  },
  {
    "dn": "cn=usMil,o=MyCa Org,c=US",
    "displayName": "US Military",
    "employeeId": "usMil",
    "fullName": "US Military",
    "lastName": "Military",
    "uid": "usMil",
    "clearances": ["TOP SECRET", "SECRET", "CONFIDENTIAL", "UNCLASSIFIED"],
    "formalAccess": ["foo"],
    "country": "USA",
    "affiliations": ["MILITARY"],
    "coi": [],
    "briefing": [],
    "formalGroup": [],
    "grantBy": [],
    "dissemControl": [],
    "organization": [],
    "dissemTo": []
  },
  {
    "dn": "cn=usCon,o=MyCa Org,c=US",
    "displayName": "US Contractor",
    "employeeId": "usCon",
    "fullName": "US Contractor",
    "lastName": "Contractor",
    "uid": "usCon",
    "clearances": ["TOP SECRET", "SECRET", "CONFIDENTIAL", "UNCLASSIFIED"],
    "formalAccess": ["foo", "bar", "baz"],
    "country": "USA",
    "affiliations": ["CONTRACTOR"],
    "coi": [],
    "briefing": [],
    "formalGroup": [],
    "grantBy": [],
    "dissemControl": [],
    "organization": [],
    "dissemTo": []
  },
  {
    "dn": "cn=usNACinGander,o=MyCa Org,c=US",
    "displayName": "US NonAgencyCivilian",
    "employeeId": "usNACinGander",
    "fullName": "US NonAgencyCivilian",
    "lastName": "NonAgencyCivilian",
    "uid": "usNACinGander",
    "clearances": ["SECRET", "CONFIDENTIAL", "UNCLASSIFIED"],
    "formalAccess": [],
    "country": "USA",
    "affiliations": ["NON-AGENCY CIVILIAN"],
    "coi": [],
    "briefing": [],
    "formalGroup": [],
    "grantBy": [],
    "dissemControl": [],
    "organization": [],
    "dissemTo": []
  },{
    "dn": "cn=usNACnotInGander,o=MyCa Org,c=US",
    "displayName": "US NonAgencyCivilian",
    "employeeId": "usNACnotInGander",
    "fullName": "US NonAgencyCivilian",
    "lastName": "NonAgencyCivilian",
    "uid": "usNACnotInGander",
    "clearances": ["SECRET", "CONFIDENTIAL", "UNCLASSIFIED"],
    "formalAccess": [],
    "country": "USA",
    "affiliations": ["NON-AGENCY CIVILIAN"],
    "coi": [],
    "briefing": [],
    "formalGroup": [],
    "grantBy": [],
    "dissemControl": [],
    "organization": [],
    "dissemTo": []
  },
  {
    "dn": "cn=usNACinZoom,o=MyCa Org,c=US",
    "displayName": "US NonAgencyCivilian",
    "employeeId": "usNACinZoom",
    "fullName": "US NonAgencyCivilian",
    "lastName": "NonAgencyCivilian",
    "uid": "usNACinZoom",
    "clearances": ["SECRET", "CONFIDENTIAL", "UNCLASSIFIED"],
    "formalAccess": [],
    "country": "USA",
    "affiliations": ["NON-AGENCY CIVILIAN"],
    "coi": [],
    "briefing": [],
    "formalGroup": [],
    "grantBy": [],
    "dissemControl": [],
    "organization": [],
    "dissemTo": []
  },
  {
    "dn": "cn=usNACnotInZoom,o=MyCa Org,c=US",
    "displayName": "US NonAgencyCivilian",
    "employeeId": "usNACnotInZoom",
    "fullName": "US NonAgencyCivilian",
    "lastName": "NonAgencyCivilian",
    "uid": "usNACnotInZoom",
    "clearances": ["SECRET", "CONFIDENTIAL", "UNCLASSIFIED"],
    "formalAccess": [],
    "country": "USA",
    "affiliations": ["NON-AGENCY CIVILIAN"],
    "coi": [],
    "briefing": [],
    "formalGroup": [],
    "grantBy": [],
    "dissemControl": [],
    "organization": [],
    "dissemTo": []
  },
  {
    "dn": "cn=usOtherAgency,o=MyCa Org,c=US",
    "displayName": "James Bond",
    "employeeId": "usOtherAgency",
    "fullName": "James Bond",
    "lastName": "Bond",
    "uid": "usOtherAgency",
    "clearances": ["SECRET", "CONFIDENTIAL", "UNCLASSIFIED"],
    "formalAccess": [],
    "country": "USA",
    "affiliations": ["NON-AGENCY"],
    "coi": [],
    "briefing": [],
    "formalGroup": [],
    "grantBy": [],
    "dissemControl": [],
    "organization": [],
    "dissemTo": []
  },
  {
    "dn": "cn=testUser1,o=MyCa Org,c=US",
    "displayName": "James Bond",
    "employeeId": "testUser1",
    "fullName": "James Bond",
    "lastName": "Bond",
    "uid": "testUser1",
    "clearances": ["TOP SECRET", "SECRET", "CONFIDENTIAL", "UNCLASSIFIED"],
    "formalAccess": ["foo", "bar", "baz"],
    "country": "USA",
    "affiliations": ["CIVILIAN"],
    "coi": [],
    "briefing": [],
    "formalGroup": [],
    "grantBy": [],
    "dissemControl": [],
    "organization": [],
    "dissemTo": []
  },
  {
    "dn": "jjdoe",
    "displayName": "John James Doe",
    "employeeId": "jjdoe",
    "fullName": "John James Doe",
    "lastName": "Doe",
    "uid": "jjdoe",
    "clearances": ["UNCLASSIFIED"],
    "formalAccess": [],
    "country": "USA",
    "affiliations": ["CONTRACTOR"],
    "coi": [],
    "briefing": [],
    "formalGroup": [],
    "grantBy": [],
    "dissemControl": [],
    "organization": [],
    "dissemTo": []
  }
]